azurefunctions/extensions/bindings/protos/__init__.py
azurefunctions/extensions/bindings/protos/settlement_pb2.py
azurefunctions/extensions/bindings/protos/settlement_pb2_grpc.py
azurefunctions/extensions/bindings/servicebus/__init__.py
azurefunctions/extensions/bindings/servicebus/grpcClient.py
azurefunctions/extensions/bindings/servicebus/grpc_utils.py
azurefunctions/extensions/bindings/servicebus/serviceBusClientConverter.py
azurefunctions/extensions/bindings/servicebus/serviceBusConverter.py
azurefunctions/extensions/bindings/servicebus/serviceBusMessageActions.py
azurefunctions/extensions/bindings/servicebus/serviceBusReceivedMessage.py
azurefunctions/extensions/bindings/servicebus/utils.py
azurefunctions_extensions_bindings_servicebus-1.0.0b2.dist-info/licenses/LICENSE
samples/servicebus_samples_batch/function_app.py
samples/servicebus_samples_settlement/function_app.py
samples/servicebus_samples_single/function_app.py
azurefunctions_extensions_bindings_servicebus-1.0.0b2.dist-info/METADATA
azurefunctions_extensions_bindings_servicebus-1.0.0b2.dist-info/WHEEL
azurefunctions_extensions_bindings_servicebus-1.0.0b2.dist-info/top_level.txt
azurefunctions_extensions_bindings_servicebus-1.0.0b2.dist-info/RECORD
