Metadata-Version: 2.4
Name: azurefunctions-extensions-bindings-servicebus
Version: 1.0.0b2
Summary: ServiceBus Python worker extension for Azure Functions.
Author-email: "Azure Functions team at Microsoft Corp." <azurefunctions@microsoft.com>
License: MIT License
Classifier: License :: OSI Approved :: MIT License
Classifier: Intended Audience :: Developers
Classifier: Programming Language :: Python :: 3
Classifier: Programming Language :: Python :: 3.9
Classifier: Programming Language :: Python :: 3.10
Classifier: Programming Language :: Python :: 3.11
Classifier: Programming Language :: Python :: 3.12
Classifier: Programming Language :: Python :: 3.13
Classifier: Operating System :: Microsoft :: Windows
Classifier: Operating System :: POSIX
Classifier: Operating System :: MacOS :: MacOS X
Classifier: Environment :: Web Environment
Classifier: Development Status :: 5 - Production/Stable
Requires-Python: >=3.9
License-File: LICENSE
Requires-Dist: azurefunctions-extensions-base>=1.1.0
Requires-Dist: azure-servicebus<8.0,>=7.14.2
Requires-Dist: uamqp<2.0,>=1.6.11
Requires-Dist: protobuf<7.0,>=6.32.0
Requires-Dist: grpcio<2.0,>=1.74.0
Requires-Dist: grpcio-tools<2.0,>=1.74.0
Provides-Extra: dev
Requires-Dist: flake8; extra == "dev"
Requires-Dist: mypy; extra == "dev"
Requires-Dist: pytest; extra == "dev"
Requires-Dist: pytest-cov; extra == "dev"
Requires-Dist: coverage; extra == "dev"
Requires-Dist: pytest-instafail; extra == "dev"
Requires-Dist: pre-commit; extra == "dev"
Dynamic: license-file
